datamart_profiler/__init__.py
datamart_profiler/__main__.py
datamart_profiler/core.py
datamart_profiler/numerical.py
datamart_profiler/profile_types.py
datamart_profiler/spatial.py
datamart_profiler/temporal.py
datamart_profiler/types.py
datamart_profiler/warning_tools.py
datamart_profiler-0.12.dist-info/licenses/LICENSE.txt
datamart_profiler-0.12.dist-info/licenses/NOTICE.txt
datamart_profiler-0.12.dist-info/METADATA
datamart_profiler-0.12.dist-info/WHEEL
datamart_profiler-0.12.dist-info/top_level.txt
datamart_profiler-0.12.dist-info/RECORD
