Metadata-Version: 2.4
Name: datamart-profiler
Version: 0.12
Summary: Data profiling library for Auctus
Home-page: https://gitlab.com/ViDA-NYU/auctus/auctus
Author: Remi Rampin
Author-email: remi.rampin@nyu.edu
Maintainer: Remi Rampin
Maintainer-email: remi.rampin@nyu.edu
License: Apache-2.0
Project-URL: Homepage, https://gitlab.com/ViDA-NYU/auctus/auctus
Project-URL: Source, https://gitlab.com/ViDA-NYU/auctus/auctus
Project-URL: Tracker, https://gitlab.com/ViDA-NYU/auctus/auctus/-/issues
Keywords: auctus,datamart
Classifier: Development Status :: 4 - Beta
Classifier: Intended Audience :: Science/Research
Classifier: License :: OSI Approved :: Apache Software License
Classifier: Operating System :: OS Independent
Classifier: Programming Language :: Python :: 3 :: Only
Classifier: Topic :: Scientific/Engineering :: Information Analysis
License-File: LICENSE.txt
License-File: NOTICE.txt
Requires-Dist: numpy
Requires-Dist: opentelemetry-api
Requires-Dist: pandas>=2.1.0
Requires-Dist: prometheus_client
Requires-Dist: python-dateutil
Requires-Dist: scikit-learn
Requires-Dist: regex
Requires-Dist: requests
Requires-Dist: datamart-geo<0.4,>=0.2.3
Dynamic: author
Dynamic: author-email
Dynamic: classifier
Dynamic: description
Dynamic: home-page
Dynamic: keywords
Dynamic: license
Dynamic: license-file
Dynamic: maintainer
Dynamic: maintainer-email
Dynamic: project-url
Dynamic: requires-dist
Dynamic: summary
